toUpper.v
`timescale 1ns / 1ps

module toUpper(A0,A1,A2,A3,A4,A5,A6,B0,B1,B2,B3,B4,B5,B6,B7);
    input A0,A1,A2,A3,A4,A5,A6;
    output B0,B1,B2,B3,B4,B5,B6,B7;

    wire nA7, nA1;
    wire L_OR;       
    wire L_AND;     
    wire L;            
    wire nL;           

    // A7' --> nA7
    not #5 (nA7, A7);
    // A1' --> nA1
    not #5 (nA1, A1);

    // A4 + A3 + A2 --> L_OR
    or  #10 (L_OR, A4, A3, A2);

    // A7' * A6 * A5 * A1' --> L_AND
    and #10 (L_AND, nA7, A6, A5, nA1);

    // Final gate of L
    and #10 (L, L_AND, L_OR);

    not #5 (nL, L);

    // Determination of B5
    and #10 (B5, A5, nL);

    // all other inputs are the same
    buf #4 (B0, A0);
    buf #4 (B1, A1);
    buf #4 (B2, A2);
    buf #4 (B3, A3);
    buf #4 (B4, A4);
    buf #4 (B6, A6);
    buf #4 (B7, A7);

endmodule

toUpper_tb.v
module toUpper_tb;

reg A0, A1, A2, A3, A4, A5, A6, A7;
wire B0, B1, B2, B3, B4, B5, B6, B7;

toUpper dut (.A0(A0), .A1(A1), .A2(A2), .A3(A3), .A4(A4), .A5(A5), .A6(A6), .A7(A7),
             .B0(B0), .B1(B1), .B2(B2), .B3(B3), .B4(B4), .B5(B5), .B6(B6), .B7(B7));

initial begin
    $dumpfile("toUpper.vcd");
    $dumpvars(0, toUpper_tb);
    
    // (
    {A7,A6,A5,A4,A3,A2,A1,A0} = 8'b00101000; #25;
    // H
    {A7,A6,A5,A4,A3,A2,A1,A0} = 8'b01001000; #25;
    // .
    {A7,A6,A5,A4,A3,A2,A1,A0} = 8'b10110111; #25;
    // f
    {A7,A6,A5,A4,A3,A2,A1,A0} = 8'b10000011; #25;
    // |
    {A7,A6,A5,A4,A3,A2,A1,A0} = 8'b01111100; #25;
    // DC4
    {A7,A6,A5,A4,A3,A2,A1,A0} = 8'b00010100; #25;
    // ë
    {A7,A6,A5,A4,A3,A2,A1,A0} = 8'b11101011; #25;
    // a
    {A7,A6,A5,A4,A3,A2,A1,A0} = 8'b01100001; #25;
    // A
    {A7,A6,A5,A4,A3,A2,A1,A0} = 8'b01000001; #25;
    // z
    {A7,A6,A5,A4,A3,A2,A1,A0} = 8'b01111010; #25;
    // G
    {A7,A6,A5,A4,A3,A2,A1,A0} = 8'b01000111; #25;
    // m
    {A7,A6,A5,A4,A3,A2,A1,A0} = 8'b01101101; #25;
    // '
    {A7,A6,A5,A4,A3,A2,A1,A0} = 8'b10010010; #25;
    // 0
    {A7,A6,A5,A4,A3,A2,A1,A0} = 8'b00110000; #25;
    // Ï
    {A7,A6,A5,A4,A3,A2,A1,A0} = 8'b11001111; #25;
    // : 
    {A7,A6,A5,A4,A3,A2,A1,A0} = 8'b00111010; #25;
    // {
    {A7,A6,A5,A4,A3,A2,A1,A0} = 8'b01111011; #25;
    // ”
    {A7,A6,A5,A4,A3,A2,A1,A0} = 8'b10010100; #25;
    // DEL
    {A7,A6,A5,A4,A3,A2,A1,A0} = 8'b01111111; #25;

    #50 $finish;
end

endmodule

toUpper.vcd
$date
	Thu Oct 30 14:31:08 2025
$end
$version
	Icarus Verilog
$end
$timescale
	1ps
$end
$scope module toUpper_tb $end
$var wire 1 ! B7 $end
$var wire 1 " B6 $end
$var wire 1 # B5 $end
$var wire 1 $ B4 $end
$var wire 1 % B3 $end
$var wire 1 & B2 $end
$var wire 1 ' B1 $end
$var wire 1 ( B0 $end
$var reg 1 ) A0 $end
$var reg 1 * A1 $end
$var reg 1 + A2 $end
$var reg 1 , A3 $end
$var reg 1 - A4 $end
$var reg 1 . A5 $end
$var reg 1 / A6 $end
$var reg 1 0 A7 $end
$scope module dut $end
$var wire 1 ) A0 $end
$var wire 1 * A1 $end
$var wire 1 + A2 $end
$var wire 1 , A3 $end
$var wire 1 - A4 $end
$var wire 1 . A5 $end
$var wire 1 / A6 $end
$var wire 1 0 A7 $end
$var wire 1 ( B0 $end
$var wire 1 ' B1 $end
$var wire 1 & B2 $end
$var wire 1 % B3 $end
$var wire 1 $ B4 $end
$var wire 1 # B5 $end
$var wire 1 " B6 $end
$var wire 1 ! B7 $end
$var wire 1 1 L $end
$var wire 1 2 L_AND $end
$var wire 1 3 L_OR $end
$var wire 1 4 nA1 $end
$var wire 1 5 nA7 $end
$var wire 1 6 nL $end
$upscope $end
$upscope $end
$enddefinitions $end
$comment Show the parameter values. $end
$dumpall
$end
#0
$dumpvars
x6
x5
x4
x3
x2
x1
00
0/
1.
0-
1,
0+
0*
0)
x(
x'
x&
x%
x$
x#
x"
x!
$end
#4000
0!
0"
0$
1%
0&
0'
0(
#5000
15
14
#10000
02
13
#20000
01
#25000
16
1/
0.
#29000
1"
#35000
0#
#50000
10
0/
1.
1-
0,
1+
1*
1)
#54000
1!
0"
1$
0%
1&
1'
1(
#55000
05
04
#60000
1#
#75000
0.
0-
0+
#79000
0$
0&
#85000
0#
03
#100000
00
1/
1.
1-
1,
1+
0*
0)
#104000
0!
1"
1$
1%
1&
0'
0(
#105000
15
14
#110000
1#
13
#115000
12
#125000
11
0/
0.
0,
#129000
0"
0%
#130000
06
#135000
02
0#
#145000
01
#150000
16
10
1/
1.
0-
1,
0+
1*
1)
#154000
1!
1"
0$
1%
0&
1'
1(
#155000
05
04
#160000
1#
#175000
00
0,
0*
#179000
0!
0%
0'
#180000
15
14
#185000
03
#190000
12
#200000
0.
#210000
02
0#
#225000
1.
1-
1,
1*
0)
#229000
1$
1%
1'
0(
#230000
04
#235000
1#
13
#250000
0.
0-
0,
1+
1)
#254000
0$
0%
1&
1(
#260000
0#
#275000
1.
1,
0*
#279000
1%
0'
#280000
14
#285000
1#
#290000
12
#300000
11
10
0/
0.
1-
0,
0+
1*
0)
#304000
1!
0"
1$
0%
0&
1'
0(
#305000
06
05
04
#310000
02
0#
#320000
01
#325000
16
00
1.
0*
#329000
0!
0'
#330000
15
14
#335000
1#
#350000
10
1/
0.
0-
1,
1+
1*
1)
#354000
1!
1"
0$
1%
1&
1'
1(
#355000
05
04
#360000
0#
#375000
00
0/
1.
1-
0+
0)
#379000
0!
0"
1$
0&
0(
#380000
15
#385000
1#
#400000
1/
1)
#404000
1"
1(
#425000
10
0/
0.
0,
1+
0*
0)
#429000
1!
0"
0%
1&
0'
0(
#430000
05
14
#435000
0#
#450000
00
1/
1.
1,
1*
1)
#454000
0!
1"
1%
1'
1(
#455000
15
04
#460000
1#
