toUpper.v
`timescale 1ns / 1ps

module toUpper(A0,A1,A2,A3,A4,A5,A6,B0,B1,B2,B3,B4,B5,B6,B7);
    input A0,A1,A2,A3,A4,A5,A6;
    output B0,B1,B2,B3,B4,B5,B6,B7;

    wire nA7, nA1;
    wire L_OR;       
    wire L_AND;     
    wire L;            
    wire nL;           

    // A7' --> nA7
    not #5 (nA7, A7);
    // A1' --> nA1
    not #5 (nA1, A1);

    // A4 + A3 + A2 --> L_OR
    or  #10 (L_OR, A4, A3, A2);

    // A7' * A6 * A5 * A1' --> L_AND
    and #10 (L_AND, nA7, A6, A5, nA1);

    // Final gate of L
    and #10 (L, L_AND, L_OR);

    not #5 (nL, L);

    // Determination of B5
    and #10 (B5, A5, nL);

    // all other inputs are the same
    buf #4 (B0, A0);
    buf #4 (B1, A1);
    buf #4 (B2, A2);
    buf #4 (B3, A3);
    buf #4 (B4, A4);
    buf #4 (B6, A6);
    buf #4 (B7, A7);

endmodule

toUpper_tb.v
`timescale 1ns / 1ps

module toUpper_tb;

reg A0, A1, A2, A3, A4, A5, A6, A7;
wire B0, B1, B2, B3, B4, B5, B6, B7;

toUpper dut (.A0(A0), .A1(A1), .A2(A2), .A3(A3), .A4(A4), .A5(A5), .A6(A6), .A7(A7),
             .B0(B0), .B1(B1), .B2(B2), .B3(B3), .B4(B4), .B5(B5), .B6(B6), .B7(B7));

initial begin
    $dumpfile("toUpper.vcd");
    $dumpvars(0, toUpper_tb);
    
    // (
    {A7,A6,A5,A4,A3,A2,A1,A0} = 8'b00101000; #10;
    // H
    {A7,A6,A5,A4,A3,A2,A1,A0} = 8'b01001000; #10;
    // .
    {A7,A6,A5,A4,A3,A2,A1,A0} = 8'b10110111; #10;
    // f
    {A7,A6,A5,A4,A3,A2,A1,A0} = 8'b10000011; #10;
    // |
    {A7,A6,A5,A4,A3,A2,A1,A0} = 8'b01111100; #10;
    // DC4
    {A7,A6,A5,A4,A3,A2,A1,A0} = 8'b00010100; #10;
    // ë
    {A7,A6,A5,A4,A3,A2,A1,A0} = 8'b11101011; #10;
    // a
    {A7,A6,A5,A4,A3,A2,A1,A0} = 8'b01100001; #10;
    // A
    {A7,A6,A5,A4,A3,A2,A1,A0} = 8'b01000001; #10;
    // z
    {A7,A6,A5,A4,A3,A2,A1,A0} = 8'b01111010; #10;
    // G
    {A7,A6,A5,A4,A3,A2,A1,A0} = 8'b01000111; #10;
    // m
    {A7,A6,A5,A4,A3,A2,A1,A0} = 8'b01101101; #10;
    // '
    {A7,A6,A5,A4,A3,A2,A1,A0} = 8'b10010010; #10;
    // 0
    {A7,A6,A5,A4,A3,A2,A1,A0} = 8'b00110000; #10;
    // Ï
    {A7,A6,A5,A4,A3,A2,A1,A0} = 8'b11001111; #10;
    // : 
    {A7,A6,A5,A4,A3,A2,A1,A0} = 8'b00111010; #10;
    // {
    {A7,A6,A5,A4,A3,A2,A1,A0} = 8'b01111011; #10;
    // ”
    {A7,A6,A5,A4,A3,A2,A1,A0} = 8'b10010100; #10;
    // DEL
    {A7,A6,A5,A4,A3,A2,A1,A0} = 8'b01111111; #10;

    #50 $finish;
end

endmodule

toUpper.vcd
$date
	Sun Nov 02 19:49:13 2025
$end
$version
	Icarus Verilog
$end
$timescale
	1ps
$end
$scope module toUpper_tb $end
$var wire 1 ! B7 $end
$var wire 1 " B6 $end
$var wire 1 # B5 $end
$var wire 1 $ B4 $end
$var wire 1 % B3 $end
$var wire 1 & B2 $end
$var wire 1 ' B1 $end
$var wire 1 ( B0 $end
$var reg 1 ) A0 $end
$var reg 1 * A1 $end
$var reg 1 + A2 $end
$var reg 1 , A3 $end
$var reg 1 - A4 $end
$var reg 1 . A5 $end
$var reg 1 / A6 $end
$var reg 1 0 A7 $end
$scope module dut $end
$var wire 1 ) A0 $end
$var wire 1 * A1 $end
$var wire 1 + A2 $end
$var wire 1 , A3 $end
$var wire 1 - A4 $end
$var wire 1 . A5 $end
$var wire 1 / A6 $end
$var wire 1 0 A7 $end
$var wire 1 ( B0 $end
$var wire 1 ' B1 $end
$var wire 1 & B2 $end
$var wire 1 % B3 $end
$var wire 1 $ B4 $end
$var wire 1 # B5 $end
$var wire 1 " B6 $end
$var wire 1 ! B7 $end
$var wire 1 1 L $end
$var wire 1 2 L_AND $end
$var wire 1 3 L_OR $end
$var wire 1 4 nA1 $end
$var wire 1 5 nA7 $end
$var wire 1 6 nL $end
$upscope $end
$upscope $end
$enddefinitions $end
$comment Show the parameter values. $end
$dumpall
$end
#0
$dumpvars
x6
x5
x4
x3
x2
x1
00
0/
1.
0-
1,
0+
0*
0)
x(
x'
x&
x%
x$
x#
x"
x!
$end
#4000
0!
0"
0$
1%
0&
0'
0(
#5000
15
14
#10000
02
13
1/
0.
#14000
1"
#20000
01
0#
10
0/
1.
1-
0,
1+
1*
1)
#24000
1!
0"
1$
0%
1&
1'
1(
#25000
16
05
04
#30000
0.
0-
0+
#34000
0$
0&
#40000
03
00
1/
1.
1-
1,
1+
0*
0)
#44000
0!
1"
1$
1%
1&
0'
0(
#45000
15
14
#50000
1#
13
0/
0.
0,
#54000
0"
0%
#60000
0#
10
1/
1.
0-
1,
0+
1*
1)
#64000
1!
1"
0$
1%
0&
1'
1(
#65000
05
04
#70000
1#
00
0,
0*
#74000
0!
0%
0'
#75000
15
14
#80000
03
0.
#90000
0#
1.
1-
1,
1*
0)
#94000
1$
1%
1'
0(
#95000
04
#100000
1#
13
0.
0-
0,
1+
1)
#104000
0$
0%
1&
1(
#110000
0#
1.
1,
0*
#114000
1%
0'
#115000
14
#120000
1#
10
0/
0.
1-
0,
0+
1*
0)
#124000
1!
0"
1$
0%
0&
1'
0(
#125000
05
04
#130000
0#
00
1.
0*
#134000
0!
0'
#135000
15
14
#140000
1#
10
1/
0.
0-
1,
1+
1*
1)
#144000
1!
1"
0$
1%
1&
1'
1(
#145000
05
04
#150000
0#
00
0/
1.
1-
0+
0)
#154000
0!
0"
1$
0&
0(
#155000
15
#160000
1#
1/
1)
#164000
1"
1(
#170000
10
0/
0.
0,
1+
0*
0)
#174000
1!
0"
0%
1&
0'
0(
#175000
05
14
#180000
0#
00
1/
1.
1,
1*
1)
#184000
0!
1"
1%
1'
1(
#185000
15
04
#190000
1#
