toUpper.v
`timescale 1ns / 1ps

module toUpper(A0,A1,A2,A3,A4,A5,A6,A7,B0,B1,B2,B3,B4,B5,B6,B7);
    input A0,A1,A2,A3,A4,A5,A6,A7;
    output B0,B1,B2,B3,B4,B5,B6,B7;

    wire nA7, nA6, nA4, nA3, nA2, nA1, nA0;
    wire term1, term2, term3, term4;
    wire sum_terms;
    wire L, nL;
    not #5 (nA7, A7);
    not #5 (nA6, A6);
    not #5 (nA4, A4);
    not #5 (nA3, A3);
    not #5 (nA2, A2);
    not #5 (nA1, A1);
    not #5 (nA0, A0);

    and #10 (term1, nA7, nA6) // A7’A6'
    and #10 (term2, nA7, A6, A4, A3, A2) // A7’A6A4A3A2
    and #10 (term3, nA7, A6, A4, A3, nA2, A1, A0) // A7’A6A4A3A2’A1A0
    and #10 (term4, nA7, nA4, nA3, nA2, nA1, nA0) // A7’A4’A3’A2’A1’A0’​

    or #10 (sum_terms, A7, term1, term2, term3, term4) // A7 ​+ A7’A6′ ​+ A7’A6A4A3A2 + A7’A6A4A3A2’A1A0 + A7’A4’A3’A2’A1’A0’
    and #10 (L, sum_terms, A5)
    
    not #5 (nL, L);

    // Determination of B5
    and #10 (B5, A5, nL);

    // all other inputs are the same
    buf #4 (B0, A0);
    buf #4 (B1, A1);
    buf #4 (B2, A2);
    buf #4 (B3, A3);
    buf #4 (B4, A4);
    buf #4 (B6, A6);
    buf #4 (B7, A7);

endmodule

toUpper_tb.v

module toUpper_tb;

reg A0, A1, A2, A3, A4, A5, A6, A7;
wire B0, B1, B2, B3, B4, B5, B6, B7;

toUpper dut (.A0(A0), .A1(A1), .A2(A2), .A3(A3), .A4(A4), .A5(A5), .A6(A6), .A7(A7),
             .B0(B0), .B1(B1), .B2(B2), .B3(B3), .B4(B4), .B5(B5), .B6(B6), .B7(B7));

initial begin
    $dumpfile("toUpper.vcd");
    $dumpvars(0, toUpper_tb);
    
    // (
    {A7,A6,A5,A4,A3,A2,A1,A0} = 8'b00101000; #15;
    // H
    {A7,A6,A5,A4,A3,A2,A1,A0} = 8'b01001000; #15;
    // .
    {A7,A6,A5,A4,A3,A2,A1,A0} = 8'b10110111; #15;
    // f
    {A7,A6,A5,A4,A3,A2,A1,A0} = 8'b10000011; #15;
    // |
    {A7,A6,A5,A4,A3,A2,A1,A0} = 8'b01111100; #15;
    // DC4
    {A7,A6,A5,A4,A3,A2,A1,A0} = 8'b00010100; #15;
    // ë
    {A7,A6,A5,A4,A3,A2,A1,A0} = 8'b11101011; #15;
    // a
    {A7,A6,A5,A4,A3,A2,A1,A0} = 8'b01100001; #15;
    // A
    {A7,A6,A5,A4,A3,A2,A1,A0} = 8'b01000001; #15;
    // z
    {A7,A6,A5,A4,A3,A2,A1,A0} = 8'b01111010; #15;
    // G
    {A7,A6,A5,A4,A3,A2,A1,A0} = 8'b01000111; #15;
    // m
    {A7,A6,A5,A4,A3,A2,A1,A0} = 8'b01101101; #15;
    // '
    {A7,A6,A5,A4,A3,A2,A1,A0} = 8'b10010010; #15;
    // 0
    {A7,A6,A5,A4,A3,A2,A1,A0} = 8'b00110000; #15;
    // Ï
    {A7,A6,A5,A4,A3,A2,A1,A0} = 8'b11001111; #15;
    // : 
    {A7,A6,A5,A4,A3,A2,A1,A0} = 8'b00111010; #15;
    // {
    {A7,A6,A5,A4,A3,A2,A1,A0} = 8'b01111011; #15;
    // ”
    {A7,A6,A5,A4,A3,A2,A1,A0} = 8'b10010100; #15;
    // DEL
    {A7,A6,A5,A4,A3,A2,A1,A0} = 8'b01111111; #15;

    #50 $finish;
end

endmodule

toUpper.vcd
$date
	Tue Nov 04 00:52:45 2025
$end
$version
	Icarus Verilog
$end
$timescale
	1ps
$end
$scope module toUpper_tb $end
$var wire 1 ! B7 $end
$var wire 1 " B6 $end
$var wire 1 # B5 $end
$var wire 1 $ B4 $end
$var wire 1 % B3 $end
$var wire 1 & B2 $end
$var wire 1 ' B1 $end
$var wire 1 ( B0 $end
$var reg 1 ) A0 $end
$var reg 1 * A1 $end
$var reg 1 + A2 $end
$var reg 1 , A3 $end
$var reg 1 - A4 $end
$var reg 1 . A5 $end
$var reg 1 / A6 $end
$var reg 1 0 A7 $end
$scope module dut $end
$var wire 1 ) A0 $end
$var wire 1 * A1 $end
$var wire 1 + A2 $end
$var wire 1 , A3 $end
$var wire 1 - A4 $end
$var wire 1 . A5 $end
$var wire 1 / A6 $end
$var wire 1 0 A7 $end
$var wire 1 ( B0 $end
$var wire 1 ' B1 $end
$var wire 1 & B2 $end
$var wire 1 % B3 $end
$var wire 1 $ B4 $end
$var wire 1 # B5 $end
$var wire 1 " B6 $end
$var wire 1 ! B7 $end
$var wire 1 1 L $end
$var wire 1 2 nA0 $end
$var wire 1 3 nA1 $end
$var wire 1 4 nA2 $end
$var wire 1 5 nA3 $end
$var wire 1 6 nA4 $end
$var wire 1 7 nA6 $end
$var wire 1 8 nA7 $end
$var wire 1 9 nL $end
$var wire 1 : sum_terms $end
$var wire 1 ; term1 $end
$var wire 1 < term2 $end
$var wire 1 = term3 $end
$var wire 1 > term4 $end
$upscope $end
$upscope $end
$enddefinitions $end
$comment Show the parameter values. $end
$dumpall
$end
#0
$dumpvars
x>
x=
x<
x;
x:
x9
x8
x7
x6
x5
x4
x3
x2
x1
00
0/
1.
0-
1,
0+
0*
0)
x(
x'
x&
x%
x$
x#
x"
x!
$end
#4000
0!
0"
0$
1%
0&
0'
0(
#5000
18
17
16
05
14
13
12
#10000
0=
0<
#15000
0>
1;
1/
0.
#19000
1"
#20000
07
#25000
1:
01
0#
#30000
19
0;
10
0/
1.
1-
0,
1+
1*
1)
#34000
1!
0"
1$
0%
1&
1'
1(
#35000
08
17
06
15
04
03
02
#40000
11
1#
#45000
09
0.
0-
0+
#49000
0$
0&
#50000
16
14
#55000
01
0#
#60000
19
00
1/
1.
1-
1,
1+
0*
0)
#64000
0!
1"
1$
1%
1&
0'
0(
#65000
18
07
06
05
04
13
12
#70000
0:
11
1#
#75000
09
1<
0/
0.
0,
#79000
0"
0%
#80000
17
15
01
#85000
19
1:
0<
0#
#90000
1;
10
1/
1.
0-
1,
0+
1*
1)
#94000
1!
1"
0$
1%
0&
1'
1(
#95000
08
07
16
05
14
03
02
#100000
11
1#
#105000
09
0;
00
0,
0*
#109000
0!
0%
0'
#110000
18
15
13
#115000
0:
0#
#120000
0.
#125000
01
#130000
19
#135000
1.
1-
1,
1*
0)
#139000
1$
1%
1'
0(
#140000
06
05
03
12
#145000
1#
#150000
0.
0-
0,
1+
1)
#154000
0$
0%
1&
1(
#155000
16
15
04
02
#160000
0#
#165000
1.
1,
0*
#169000
1%
0'
#170000
05
13
#175000
1#
#180000
10
0/
0.
1-
0,
0+
1*
0)
#184000
1!
0"
1$
0%
0&
1'
0(
#185000
08
17
06
15
14
03
12
#190000
1:
0#
#195000
00
1.
0*
#199000
0!
0'
#200000
18
13
#205000
0:
11
1#
#210000
09
1;
10
1/
0.
0-
1,
1+
1*
1)
#214000
1!
1"
0$
1%
1&
1'
1(
#215000
08
07
16
05
04
03
02
01
#220000
19
1:
0#
#225000
0;
00
0/
1.
1-
0+
0)
#229000
0!
0"
1$
0&
0(
#230000
18
17
06
14
12
#235000
0:
11
1#
#240000
09
1;
1/
1)
#244000
1"
1(
#245000
07
02
01
#250000
19
1:
1=
0#
#255000
0;
10
0/
0.
0,
1+
0*
0)
#259000
1!
0"
0%
1&
0'
0(
#260000
08
17
15
04
13
12
#265000
0=
#270000
00
1/
1.
1,
1*
1)
#274000
0!
1"
1%
1'
1(
#275000
18
07
05
03
02
#280000
0:
11
1#
#285000
09
1<
#290000
01
#295000
19
1:
0#
#305000
1#
11
#310000
09
#320000
0#
