toUpper.v
`timescale 1ns / 1ps

module toUpper(A0,A1,A2,A3,A4,A5,A6,A7,B0,B1,B2,B3,B4,B5,B6,B7);
    input A0,A1,A2,A3,A4,A5,A6,A7;
    output B0,B1,B2,B3,B4,B5,B6,B7;

    wire nA7, nA6, nA4, nA3, nA2, nA1, nA0;
    wire term1, term2, term3, term4;
    wire sum_terms;
    wire L, nL;
    not #5 (nA7, A7);
    not #5 (nA6, A6);
    not #5 (nA4, A4);
    not #5 (nA3, A3);
    not #5 (nA2, A2);
    not #5 (nA1, A1);
    not #5 (nA0, A0);

    and #10 (term1, nA7, nA6); // A7’A6'
    and #10 (term2, nA7, A6, A4, A3, A2); // A7’A6A4A3A2
    and #10 (term3, nA7, A6, A4, A3, nA2, A1, A0); // A7’A6A4A3A2’A1A0
    and #10 (term4, nA7, nA4, nA3, nA2, nA1, nA0); // A7’A4’A3’A2’A1’A0’​

    or #10 (sum_terms, A7, term1, term2, term3, term4); // A7 ​+ A7’A6′ ​+ A7’A6A4A3A2 + A7’A6A4A3A2’A1A0 + A7’A4’A3’A2’A1’A0’
    and #10 (L, sum_terms, A5);
    
    not #5 (nL, L);

    // Determination of B5
    and #10 (B5, A5, nL);

    // all other inputs are the same
    buf #4 (B0, A0);
    buf #4 (B1, A1);
    buf #4 (B2, A2);
    buf #4 (B3, A3);
    buf #4 (B4, A4);
    buf #4 (B6, A6);
    buf #4 (B7, A7);

endmodule

toUpper_tb.v
module toUpper_tb;

reg A0, A1, A2, A3, A4, A5, A6, A7;
wire B0, B1, B2, B3, B4, B5, B6, B7;

toUpper dut (.A0(A0), .A1(A1), .A2(A2), .A3(A3), .A4(A4), .A5(A5), .A6(A6), .A7(A7),
             .B0(B0), .B1(B1), .B2(B2), .B3(B3), .B4(B4), .B5(B5), .B6(B6), .B7(B7));

initial begin
    $dumpfile("toUpper.vcd");
    $dumpvars(0, toUpper_tb);
    
    // (
    {A7,A6,A5,A4,A3,A2,A1,A0} = 8'b00101000; #25;
    // H
    {A7,A6,A5,A4,A3,A2,A1,A0} = 8'b01001000; #25;
    // .
    {A7,A6,A5,A4,A3,A2,A1,A0} = 8'b10110111; #25;
    // f
    {A7,A6,A5,A4,A3,A2,A1,A0} = 8'b10000011; #25;
    // |
    {A7,A6,A5,A4,A3,A2,A1,A0} = 8'b01111100; #25;
    // DC4
    {A7,A6,A5,A4,A3,A2,A1,A0} = 8'b00010100; #25;
    // ë
    {A7,A6,A5,A4,A3,A2,A1,A0} = 8'b11101011; #25;
    // a
    {A7,A6,A5,A4,A3,A2,A1,A0} = 8'b01100001; #25;
    // A
    {A7,A6,A5,A4,A3,A2,A1,A0} = 8'b01000001; #25;
    // z
    {A7,A6,A5,A4,A3,A2,A1,A0} = 8'b01111010; #25;
    // G
    {A7,A6,A5,A4,A3,A2,A1,A0} = 8'b01000111; #25;
    // m
    {A7,A6,A5,A4,A3,A2,A1,A0} = 8'b01101101; #25;
    // '
    {A7,A6,A5,A4,A3,A2,A1,A0} = 8'b10010010; #25;
    // 0
    {A7,A6,A5,A4,A3,A2,A1,A0} = 8'b00110000; #25;
    // Ï
    {A7,A6,A5,A4,A3,A2,A1,A0} = 8'b11001111; #25;
    // : 
    {A7,A6,A5,A4,A3,A2,A1,A0} = 8'b00111010; #25;
    // {
    {A7,A6,A5,A4,A3,A2,A1,A0} = 8'b01111011; #25;
    // ”
    {A7,A6,A5,A4,A3,A2,A1,A0} = 8'b10010100; #25;
    // DEL
    {A7,A6,A5,A4,A3,A2,A1,A0} = 8'b01111111; #25;

    #50 $finish;
end

endmodule

toUpper.vcd
$date
	Tue Nov  4 00:34:16 2025
$end
$version
	Icarus Verilog
$end
$timescale
	1ps
$end
$scope module toUpper_tb $end
$var wire 1 ! B7 $end
$var wire 1 " B6 $end
$var wire 1 # B5 $end
$var wire 1 $ B4 $end
$var wire 1 % B3 $end
$var wire 1 & B2 $end
$var wire 1 ' B1 $end
$var wire 1 ( B0 $end
$var reg 1 ) A0 $end
$var reg 1 * A1 $end
$var reg 1 + A2 $end
$var reg 1 , A3 $end
$var reg 1 - A4 $end
$var reg 1 . A5 $end
$var reg 1 / A6 $end
$var reg 1 0 A7 $end
$scope module dut $end
$var wire 1 ) A0 $end
$var wire 1 * A1 $end
$var wire 1 + A2 $end
$var wire 1 , A3 $end
$var wire 1 - A4 $end
$var wire 1 . A5 $end
$var wire 1 / A6 $end
$var wire 1 0 A7 $end
$var wire 1 ( B0 $end
$var wire 1 ' B1 $end
$var wire 1 & B2 $end
$var wire 1 % B3 $end
$var wire 1 $ B4 $end
$var wire 1 # B5 $end
$var wire 1 " B6 $end
$var wire 1 ! B7 $end
$var wire 1 1 L $end
$var wire 1 2 nA0 $end
$var wire 1 3 nA1 $end
$var wire 1 4 nA2 $end
$var wire 1 5 nA3 $end
$var wire 1 6 nA4 $end
$var wire 1 7 nA6 $end
$var wire 1 8 nA7 $end
$var wire 1 9 nL $end
$var wire 1 : sum_terms $end
$var wire 1 ; term1 $end
$var wire 1 < term2 $end
$var wire 1 = term3 $end
$var wire 1 > term4 $end
$upscope $end
$upscope $end
$enddefinitions $end
$comment Show the parameter values. $end
$dumpall
$end
#0
$dumpvars
x>
x=
x<
x;
x:
x9
x8
x7
x6
x5
x4
x3
x2
x1
00
0/
1.
0-
1,
0+
0*
0)
x(
x'
x&
x%
x$
x#
x"
x!
$end
#4000
0!
0"
0$
1%
0&
0'
0(
#5000
18
17
16
05
14
13
12
#10000
0=
0<
#15000
0>
1;
#25000
1:
1/
0.
#29000
1"
#30000
07
#35000
01
0#
#40000
19
0;
#50000
0:
10
0/
1.
1-
0,
1+
1*
1)
#54000
1!
0"
1$
0%
1&
1'
1(
#55000
08
17
06
15
04
03
02
#60000
1:
1#
#70000
11
#75000
09
0.
0-
0+
#79000
0$
0&
#80000
16
14
#85000
01
0#
#90000
19
#100000
00
1/
1.
1-
1,
1+
0*
0)
#104000
0!
1"
1$
1%
1&
0'
0(
#105000
18
07
06
05
04
13
12
#110000
0:
11
1#
#115000
09
1<
#120000
01
#125000
19
1:
0#
0/
0.
0,
#129000
0"
0%
#130000
17
15
#135000
0<
#140000
1;
#150000
10
1/
1.
0-
1,
0+
1*
1)
#154000
1!
1"
0$
1%
0&
1'
1(
#155000
08
07
16
05
14
03
02
#160000
11
1#
#165000
09
0;
#175000
0#
00
0,
0*
#179000
0!
0%
0'
#180000
18
15
13
#185000
0:
#195000
01
#200000
19
0.
#225000
1.
1-
1,
1*
0)
#229000
1$
1%
1'
0(
#230000
06
05
03
12
#235000
1#
#250000
0.
0-
0,
1+
1)
#254000
0$
0%
1&
1(
#255000
16
15
04
02
#260000
0#
#275000
1.
1,
0*
#279000
1%
0'
#280000
05
13
#285000
1#
#300000
10
0/
0.
1-
0,
0+
1*
0)
#304000
1!
0"
1$
0%
0&
1'
0(
#305000
08
17
06
15
14
03
12
#310000
1:
0#
#325000
00
1.
0*
#329000
0!
0'
#330000
18
13
#335000
0:
11
1#
#340000
09
1;
#345000
01
#350000
19
1:
0#
10
1/
0.
0-
1,
1+
1*
1)
#354000
1!
1"
0$
1%
1&
1'
1(
#355000
08
07
16
05
04
03
02
#365000
0;
#375000
00
0/
1.
1-
0+
0)
#379000
0!
0"
1$
0&
0(
#380000
18
17
06
14
12
#385000
0:
11
1#
#390000
09
1;
#395000
01
#400000
19
1:
0#
1/
1)
#404000
1"
1(
#405000
07
02
#410000
1=
1#
11
#415000
09
0;
#425000
0#
10
0/
0.
0,
1+
0*
0)
#429000
1!
0"
0%
1&
0'
0(
#430000
08
17
15
04
13
12
#435000
0=
01
#440000
19
#450000
00
1/
1.
1,
1*
1)
#454000
0!
1"
1%
1'
1(
#455000
18
07
05
03
02
#460000
0:
11
1#
#465000
09
1<
#470000
01
#475000
19
1:
0#
#485000
1#
11
#490000
09
#500000
0#
