toUpper.v
`timescale 1ns / 1ps

module toUpper(A, B);
    input [7:0] A;
    output [7:0] B;

    wire [7:0] nA;
    wire term0, term1, term2, term3, term4;

    not #5 (nA[7], A[7]);
    not #5 (nA[6], A[6]);
    not #5 (nA[5], A[5]);
    not #5 (nA[4], A[4]);
    not #5 (nA[3], A[3]);
    not #5 (nA[2], A[2]);
    not #5 (nA[1], A[1]);
    not #5 (nA[0], A[0]);

    // Logic terms (sum of products)
    and #10 (term0, A[5], A[7]);                                 // A5A7
    and #10 (term1, A[5], nA[6], nA[7]);                         // A5A6'A7'
    and #10 (term2, nA[7], A[6], A[5], A[4], A[3], A[2]);        // A7’A6A5A4A3A2
    and #10 (term3, nA[7], A[5], nA[4], nA[3], nA[2], nA[1], nA[0]); // A7’A5A4’A3’A2’A1’A0’
    and #10 (term4, nA[7], A[6], A[5], A[4], A[3], nA[2], A[1], A[0]); // A7'A6A5A4A3A2'A1A0

    or  #10 (B[5], term0, term1, term2, term3, term4);

    // Other bits unchanged
    assign B[7:6] = A[7:6];
    assign B[4:0] = A[4:0];

endmodule

toUpper_tb.v
`timescale 1ns / 1ps

module toUpper_tb;

    reg [7:0] A;
    wire [7:0] B;

    toUpper uut (.A(A), .B(B));

    reg [7:0] test [0:18];
    integer i;
    integer passed = 0;
    integer failed = 0;
    reg [7:0] expected;
    reg [7:0] val;

    initial begin
        $dumpfile("toUpper.vcd");
        $dumpvars(0, toUpper_tb);
    end

    initial begin
        test[0]=8'd40; 
        test[1]=8'd72; 
        test[2]=8'd183; 
        test[3]=8'd131;
        test[4]=8'd124; 
        test[5]=8'd20; 
        test[6]=8'd235; 
        test[7]=8'd97;
        test[8]=8'd65; 
        test[9]=8'd122; 
        test[10]=8'd71; 
        test[11]=8'd109;
        test[12]=8'd146; 
        test[13]=8'd48; 
        test[14]=8'd207; 
        test[15]=8'd58;
        test[16]=8'd123; 
        test[17]=8'd148; 
        test[18]=8'd127;

        for (i = 0; i < 19; i = i + 1) begin
            val = test[i];
            A = val;
            expected = (val >= 8'd97 && val <= 8'd122) ? (val & 8'hDF) : val;
            #50;

            if (B === expected) begin
                passed = passed + 1;
            end 
            else begin
                failed = failed + 1;
                $display("FAIL: input %0d ('%c'), expected %0d ('%c'), got %0d ('%c')",
                         val, val, expected, expected, B, B);
            end
        end

        $display("\nRESULT: %0d passed, %0d failed", passed, failed);
        $finish;
    end

endmodule

toUpper.vcd
$date
	Thu Nov 06 15:43:20 2025
$end
$version
	Icarus Verilog
$end
$timescale
	1ps
$end
$scope module toUpper_tb $end
$var wire 8 ! B [7:0] $end
$var reg 8 " A [7:0] $end
$var reg 8 # expected [7:0] $end
$var reg 8 $ val [7:0] $end
$var integer 32 % failed [31:0] $end
$var integer 32 & i [31:0] $end
$var integer 32 ' passed [31:0] $end
$scope module uut $end
$var wire 8 ( A [7:0] $end
$var wire 1 ) term0 $end
$var wire 1 * term1 $end
$var wire 1 + term2 $end
$var wire 1 , term3 $end
$var wire 1 - term4 $end
$var wire 8 . nA [7:0] $end
$var wire 8 / B [7:0] $end
$upscope $end
$upscope $end
$enddefinitions $end
$comment Show the parameter values. $end
$dumpall
$end
#0
$dumpvars
b0x01000 /
bx .
x-
x,
x+
x*
x)
b101000 (
b0 '
b0 &
b0 %
b101000 $
b101000 #
b101000 "
b0x01000 !
$end
#5000
b11010111 .
#10000
0+
0-
0)
#15000
0,
1*
#25000
b101000 !
b101000 /
#50000
b1101000 !
b1101000 /
b1001000 #
b1001000 "
b1001000 (
b1001000 $
b1 &
b1 '
#55000
b10110111 .
#60000
0*
#70000
b1001000 !
b1001000 /
#100000
b10010111 !
b10010111 /
b10110111 #
b10110111 "
b10110111 (
b10110111 $
b10 &
b10 '
#105000
b1001000 .
#110000
1)
#120000
b10110111 !
b10110111 /
#150000
b10100011 !
b10100011 /
b10000011 #
b10000011 "
b10000011 (
b10000011 $
b11 &
b11 '
#155000
b1111100 .
#160000
0)
#170000
b10000011 !
b10000011 /
#200000
b1011100 !
b1011100 /
b1111100 #
b1111100 "
b1111100 (
b1111100 $
b100 &
b100 '
#205000
b10000011 .
#215000
1+
#225000
b1111100 !
b1111100 /
#250000
b110100 !
b110100 /
b10100 #
b10100 "
b10100 (
b10100 $
b101 &
b101 '
#255000
b11101011 .
#260000
0+
#270000
b10100 !
b10100 /
#300000
b11001011 !
b11001011 /
b11101011 #
b11101011 "
b11101011 (
b11101011 $
b110 &
b110 '
#305000
b10100 .
#310000
1)
#320000
b11101011 !
b11101011 /
#350000
b1100001 !
b1100001 /
b1000001 #
b1100001 "
b1100001 (
b1100001 $
b111 &
b111 '
#355000
b10011110 .
#360000
0)
#370000
b1000001 !
b1000001 /
#400000
b1000001 "
b1000001 (
b1000001 $
b1000 &
b1000 '
#405000
b10111110 .
#450000
b1011010 !
b1011010 /
b1011010 #
b1111010 "
b1111010 (
b1111010 $
b1001 &
b1001 '
#455000
b10000101 .
#500000
b1000111 !
b1000111 /
b1000111 #
b1000111 "
b1000111 (
b1000111 $
b1010 &
b1010 '
#505000
b10111000 .
#550000
b1001101 !
b1001101 /
b1001101 #
b1101101 "
b1101101 (
b1101101 $
b1011 &
b1011 '
#555000
b10010010 .
#600000
b10010010 !
b10010010 /
b10010010 #
b10010010 "
b10010010 (
b10010010 $
b1100 &
b1100 '
#605000
b1101101 .
#650000
b10000 !
b10000 /
b110000 #
b110000 "
b110000 (
b110000 $
b1101 &
b1101 '
#655000
b11001111 .
#665000
1*
#675000
b110000 !
b110000 /
#700000
b11101111 !
b11101111 /
b11001111 #
b11001111 "
b11001111 (
b11001111 $
b1110 &
b1110 '
#705000
b110000 .
#710000
0*
#720000
b11001111 !
b11001111 /
#750000
b11010 !
b11010 /
b111010 #
b111010 "
b111010 (
b111010 $
b1111 &
b1111 '
#755000
b11000101 .
#765000
1*
#775000
b111010 !
b111010 /
#800000
b1111011 !
b1111011 /
b1111011 #
b1111011 "
b1111011 (
b1111011 $
b10000 &
b10000 '
#805000
b10000100 .
#810000
1-
#815000
0*
#850000
b10110100 !
b10110100 /
b10010100 #
b10010100 "
b10010100 (
b10010100 $
b10001 &
b10001 '
#855000
b1101011 .
#860000
0-
#870000
b10010100 !
b10010100 /
#900000
b1011111 !
b1011111 /
b1111111 #
b1111111 "
b1111111 (
b1111111 $
b10010 &
b10010 '
#905000
b10000000 .
#915000
1+
#925000
b1111111 !
b1111111 /
#950000
b10011 &
b10011 '
